funppy/__init__.py
funppy/debugtalk_pb2.py
funppy/debugtalk_pb2_grpc.py
funppy/examples/debugtalk.py
funppy/plugin.py
funppy-0.5.2.dist-info/LICENSE
funppy-0.5.2.dist-info/METADATA
funppy-0.5.2.dist-info/WHEEL
funppy-0.5.2.dist-info/RECORD
